asic-world/d_flip_flop/dff.v
/*
D flip flop with async reset
*/

module dff(
clk,    // clock
rst,    // reset
pre,    // preset
d,      // input signal
q,      // output
nq      // not q
);

input clk;
input rst;
input pre;
input d;

output q;
output nq;

wire clk;
wire rst;
wire pre;
wire d;

reg q;
// reg nq; this won't work

// nq always the opposite of q
assign nq = ~q;

always @ (posedge rst or posedge clk)
begin
    // in posedge rst only this line can be executed, since rst will be 1.
    // desired since rst signal shouldn't change anything else.
    if (rst == 1'b1) begin
        q <= 0;
    end else if (pre == 1'b1) begin
        q <= 1;
    end else begin
        q <= d;
    end
end

endmodule

asic-world/d_flip_flop/dff_tb.v
`include "dff.v"

module dff_tb(
clk,    // clock
rst,    // reset
pre,    // preset
d,      // input signal
q,      // output
nq      // not q
);

output clk;
output rst;
output pre;
output d;

input q;
input nq;

reg clk;
reg rst;
reg pre;
reg d;

wire q;
wire nq;

always begin
    #5 clk = ~clk;
end

initial begin
    $dumpfile("dff_tb.vcd");
    $dumpvars(0, dff_tb);
    $display("time\tclk\trst\tpre\td\tq");
    $monitor("%g\t%b\t%b\t%b\t%b\t%b", $time, clk, rst, pre, d, q);

    clk = 0;
    rst = 0;
    pre = 0;
    d = 0;

    #10 d = 1;
    #10 d = 0;
    #10 pre = 1;
    #10 rst = 1;
    #10 d = 1;
    #10 rst = 0;
        pre = 0;
    #10 $finish;
end

dff test_dff(
.clk    (clk),
.rst    (rst),
.pre    (pre),
.d      (d),
.q      (q),
.nq     ()  // not connected
);

endmodule

asic-world/d_flip_flop/dff_tb.vcd
$date
	Wed Jan 31 11:19:46 2024
$end
$version
	Icarus Verilog
$end
$timescale
	1s
$end
$scope module dff_tb $end
$var wire 1 ! nq $end
$var wire 1 " q $end
$var reg 1 # clk $end
$var reg 1 $ d $end
$var reg 1 % pre $end
$var reg 1 & rst $end
$scope module test_dff $end
$var wire 1 # clk $end
$var wire 1 $ d $end
$var wire 1 ' nq $end
$var wire 1 % pre $end
$var wire 1 & rst $end
$var reg 1 " q $end
$upscope $end
$upscope $end
$enddefinitions $end
$comment Show the parameter values. $end
$dumpall
$end
#0
$dumpvars
x'
0&
0%
0$
0#
x"
z!
$end
#5
1'
0"
1#
#10
0#
1$
#15
0'
1"
1#
#20
0#
0$
#25
1'
0"
1#
#30
0#
1%
#35
0'
1"
1#
#40
1'
0"
0#
1&
#45
1#
#50
0#
1$
#55
1#
#60
0#
0%
0&
#65
0'
1"
1#
