alinx/mux/mux.v
/*
mux, or multiplexer.

outputs one of the signals from a, b, c, d, based on the sel input.

the output is updated every time an input changes.
*/

module mux(
a,
b,
c,
d,
sel,
mout
);

input a;
input b;
input c;
input d;
input [1:0] sel;

output mout;

wire a;
wire b;
wire c;
wire d;
wire [1:0] sel;

reg mout;

always @(sel or a or b or c or d)
begin
    case(sel)
        2'b00 : mout = a;
        2'b01 : mout = b;
        2'b10 : mout = c;
        2'b11 : mout = d;
    endcase
end

endmodule

alinx/mux/mux_tb.v
`include "mux.v"
`timescale 1 ns/1 ns

module mux_tb(
a,
b,
c,
d,
sel,
mout
);

output a;
output b;
output c;
output d;
output [1:0] sel;

input mout;

reg a;
reg b;
reg c;
reg d;
reg [1:0] sel;

wire mout;

initial begin
    $dumpfile("mux_tb.vcd");
    $dumpvars(0, mux_tb);
    a = 0;
    b = 0;
    c = 0;
    d = 0;
    sel = 2'b00;
    #1000 sel = 2'b01;
    #1000 sel = 2'b10;
    #1000 sel = 2'b11;
    #1000 $finish;
end

always #({$random} % 100) a = ~a;
always #({$random} % 100) b = ~b;
always #({$random} % 100) c = ~c;
always #({$random} % 100) d = ~d;

mux test_mux(
.a      (a),
.b      (b),
.c      (c),
.d      (d),
.sel    (sel),
.mout   (mout)
);

endmodule

alinx/mux/mux_tb.vcd
$date
	Wed Feb  7 09:14:18 2024
$end
$version
	Icarus Verilog
$end
$timescale
	1ns
$end
$scope module mux_tb $end
$var wire 1 ! mout $end
$var reg 1 " a $end
$var reg 1 # b $end
$var reg 1 $ c $end
$var reg 1 % d $end
$var reg 2 & sel [1:0] $end
$scope module test_mux $end
$var wire 1 " a $end
$var wire 1 # b $end
$var wire 1 $ c $end
$var wire 1 % d $end
$var wire 2 ' sel [1:0] $end
$var reg 1 ! mout $end
$upscope $end
$upscope $end
$enddefinitions $end
$comment Show the parameter values. $end
$dumpall
$end
#0
$dumpvars
b0 '
b0 &
0%
0$
0#
0"
0!
$end
#48
1!
1"
#57
1$
#87
1%
#97
1#
#105
0!
0"
#112
0%
#114
0$
#132
1$
#141
1%
#166
1!
1"
#170
0%
#178
0!
0"
#179
0#
#204
1!
1"
#226
0!
0"
#229
0$
#259
1%
#276
1#
#284
1$
#311
1!
1"
#315
0#
#353
0%
#361
0!
0"
#370
0$
#383
1#
#406
1%
#412
0#
#435
1#
#445
1!
1"
#463
1$
#473
0!
0"
#487
1!
1"
#495
0%
#499
0$
#508
0!
0"
#517
1%
#525
0#
#530
1$
#569
1!
1"
#580
1#
#600
0%
#607
0!
0"
#615
0$
#662
1$
0#
#681
1%
#686
1!
1"
#689
0%
#692
0!
0"
#719
1%
#723
0%
#728
0$
#732
1#
#749
1!
1"
#759
0#
#763
1%
#777
1$
#785
1#
#815
0!
0"
#818
1!
1"
#841
0$
#849
0%
#851
0!
0"
#879
0#
#882
1$
#924
0$
1%
#925
0%
#942
1!
1"
#973
1#
#976
0!
0"
#977
1$
#986
1%
#1000
1!
b1 &
b1 '
#1006
0%
#1021
0!
0#
#1032
0$
#1049
1%
#1055
1"
#1064
1!
1#
#1068
0%
#1096
1$
#1120
1%
#1125
0!
0#
#1152
0"
#1165
0%
#1167
0$
#1171
1$
#1179
1%
#1195
1!
1#
#1202
0$
#1204
0%
#1216
1"
#1245
1%
#1253
0!
0#
#1264
1$
#1269
0"
#1284
0%
#1297
0$
#1327
1%
#1328
1!
1#
#1333
1"
#1338
0!
0#
#1350
1$
#1384
0$
#1390
0%
#1396
1!
1#
#1414
0!
0#
#1416
1%
#1425
0"
#1429
1!
1#
#1480
1$
#1504
1"
#1507
0%
#1516
0!
0#
#1518
1%
#1520
0"
#1534
1"
#1555
0"
#1564
1"
#1567
0$
#1587
1!
1#
#1610
0"
#1616
0%
#1632
1$
#1673
1%
#1680
0!
0#
#1685
1"
#1688
0$
#1698
1!
1#
#1702
1$
#1714
0!
0#
#1741
0%
#1743
1!
1#
#1748
0$
#1754
1$
#1760
0"
#1774
1"
#1793
0!
0#
#1824
1%
#1841
0$
#1868
0"
#1869
1$
#1872
1"
#1877
1!
1#
#1888
0"
#1889
0%
#1918
0!
0#
#1920
0$
#1926
1%
#1939
1"
#1947
1!
1#
#1969
0"
#1973
1$
#1976
0%
#2000
b10 &
b10 '
#2022
1"
#2029
0"
#2030
1"
#2033
0#
#2059
0!
0$
#2068
1%
#2074
0"
#2085
1"
#2089
1#
#2095
0"
#2121
0%
#2135
1!
1$
#2146
1%
#2151
1"
#2161
0#
#2176
0!
0$
#2190
0%
#2191
1#
#2233
0"
#2241
1!
1$
#2251
0!
0$
#2252
1"
#2268
1%
#2269
0%
#2283
0#
#2309
1!
1$
#2323
1%
#2328
1#
#2334
0"
#2356
0#
#2357
0%
#2388
0!
0$
#2412
1"
#2418
1%
1#
#2428
1!
1$
#2472
0%
#2482
0"
#2483
0!
0$
#2486
0#
#2487
1%
#2489
1!
1$
#2495
1#
#2503
1"
#2505
0#
#2518
0!
0$
0%
#2526
1#
#2531
1%
#2535
0"
#2567
1"
#2579
0#
#2584
0%
#2590
1#
#2592
0#
#2599
1!
1$
#2627
0!
0$
#2630
0"
#2631
1"
#2660
1%
#2662
0%
#2666
1#
#2672
0#
#2689
1%
#2696
1!
1$
#2710
0!
0$
#2713
0"
#2714
1#
#2726
0#
#2766
1!
1$
#2768
1#
#2778
0%
#2802
1"
#2812
0"
#2839
0#
#2841
1%
#2849
0!
0$
#2858
1"
#2871
1!
1$
1#
#2918
0"
#2922
0%
#2925
0!
0$
#2940
1%
#2942
0#
#2954
1#
#2961
0%
#2966
0#
#2983
1%
#3000
1!
b11 &
b11 '
#3003
1#
#3007
1$
#3012
1"
#3044
0!
0%
#3046
0$
#3063
1$
#3075
0"
#3079
1!
1%
#3081
0#
#3112
1#
#3129
0$
#3172
1"
#3174
0!
0%
#3184
1!
1%
#3191
1$
#3208
0#
#3231
0"
#3232
0$
#3234
1$
#3261
1"
#3267
0$
#3280
0!
0%
#3283
1$
1#
#3309
0"
#3329
1!
1%
#3336
0$
#3353
0#
#3356
1"
#3363
1#
#3365
0!
0%
#3411
0"
#3417
0#
#3427
1$
#3433
0$
#3445
1!
1%
#3450
0!
0%
#3453
1$
#3454
0$
#3469
1#
#3498
1"
#3503
1!
1%
#3505
1$
#3514
0#
#3518
0"
#3522
0!
0%
#3533
1#
#3558
0$
#3574
1"
#3594
1!
1%
#3611
0#
#3630
1$
#3664
0"
#3688
0!
0%
#3692
1#
#3699
0$
#3709
1"
#3752
0"
#3773
0#
#3779
1!
1%
#3796
1$
#3832
1#
#3834
0!
0%
#3848
1"
#3869
0$
#3885
0"
#3893
0#
#3906
1"
#3913
1!
1%
#3918
1$
#3932
0"
#3946
0!
0%
#3960
1!
1%
#3965
0$
#3967
1#
#3998
0!
0%
